ssler/ssler.py
ssler-0.0.2.dist-info/METADATA
ssler-0.0.2.dist-info/WHEEL
ssler-0.0.2.dist-info/entry_points.txt
ssler-0.0.2.dist-info/top_level.txt
ssler-0.0.2.dist-info/RECORD
