Metadata-Version: 2.1
Name: ssler
Version: 0.0.2
Summary: Easy SSL for your localhost server
Home-page: https://github.com/meain/ssler
Author: Abin Simon
Author-email: abinsimon10@gmail.com
License: UNKNOWN
Keywords: ssl,python,localhost
Platform: UNKNOWN
Classifier: Programming Language :: Python :: 3
Classifier: License :: OSI Approved :: MIT License
Classifier: Operating System :: OS Independent
Requires-Dist: flask
Requires-Dist: requests
